first_ego_mess_server-0.1.3.data/scripts/server_run
server/__init__.py
server/run_server.py
server/common/__init__.py
server/common/decorators.py
server/common/descriptor.py
server/common/errors.py
server/common/meta.py
server/common/utils.py
server/common/variables.py
server/common/img/arrow_down.png
server/common/img/arrow_up.png
server/common/img/exit.png
server/common/img/history.png
server/common/img/img.jpg
server/common/img/msg_clear.png
server/common/img/msg_send.png
server/common/img/preferences.png
server/common/img/refresh.png
server/common/img/refresh_2.png
server/common/img/search_folder.png
server/common/img/search_folder_2.png
server/common/img/search_icon.png
server/common/img/user_add.png
server/common/img/user_remove.png
server/common/qss/__init__.py
server/common/qss/animated_close_btn.py
server/common/qss/style.py
server/db/__init__.py
server/db/client_db_config.py
server/db/server_db_config.py
server/logs/__init__.py
server/logs/client_log_config.py
server/logs/server_log_config.py
server/server/__init__.py
server/server/add_user.py
server/server/config_window.py
server/server/core.py
server/server/main_window.py
server/server/remove_user.py
server/server/stat_window.py
server/unit_tests/__init__.py
server/unit_tests/test_client.py
server/unit_tests/test_server.py
server/unit_tests/test_utils.py
first_ego_mess_server-0.1.3.dist-info/METADATA
first_ego_mess_server-0.1.3.dist-info/WHEEL
first_ego_mess_server-0.1.3.dist-info/top_level.txt
first_ego_mess_server-0.1.3.dist-info/RECORD
